src/example_package_narfasec/__init__.py
src/example_package_narfasec/entry.py
src/example_package_narfasec/example.py
narfasec_test-0.2.0.dist-info/entry_points.txt
narfasec_test-0.2.0.dist-info/LICENSE
narfasec_test-0.2.0.dist-info/WHEEL
narfasec_test-0.2.0.dist-info/METADATA
narfasec_test-0.2.0.dist-info/RECORD
