Metadata-Version: 2.1
Name: narfasec-test
Version: 0.2.0
Summary: Just a test
Author: narfasec
Requires-Python: >=3.9,<4.0
Classifier: Programming Language :: Python :: 3
Classifier: Programming Language :: Python :: 3.9
Classifier: Programming Language :: Python :: 3.10
Classifier: Programming Language :: Python :: 3.11
